otel_pyautoinstrumentor/__init__.py
otel_pyautoinstrumentor/sysmon_autoinstumentor.py
otel_pyautoinstrumentor-0.1.2.dist-info/METADATA
otel_pyautoinstrumentor-0.1.2.dist-info/WHEEL
otel_pyautoinstrumentor-0.1.2.dist-info/top_level.txt
otel_pyautoinstrumentor-0.1.2.dist-info/RECORD
