Metadata-Version: 2.4
Name: otel_pyautoinstrumentor
Version: 0.1.2
Summary: Python auto instrumentor for opentelemetry
Author-email: le-codeur-rapide <paul.vezia@gmail.com>
License: MIT
Classifier: Programming Language :: Python :: 3
Classifier: License :: OSI Approved :: MIT License
Classifier: Operating System :: OS Independent
Requires-Python: >=3.12
Requires-Dist: opentelemetry-sdk>=1.34.0
Requires-Dist: opentelemetry-exporter-otlp>=1.34.0
Provides-Extra: dev
